nightray/__init__.py
nightray/main.py
nightray-0.0.0.0.dist-info/LICENSE
nightray-0.0.0.0.dist-info/METADATA
nightray-0.0.0.0.dist-info/WHEEL
nightray-0.0.0.0.dist-info/entry_points.txt
nightray-0.0.0.0.dist-info/top_level.txt
nightray-0.0.0.0.dist-info/RECORD
